{
"lts6xgvjoawxrb2qh6p5gi3z":["devopsguys","Rohit Ghumare | That #DevOps Guy✍️"],
"zpgk7732rgahyqdwz5jjhs7i":["firlep","Firlep Ghul"],
"avyax7bnjcie4atv7f4gz5pa":["ghus","Ghüs"],
"r63key5ilrlzklg2sqcocgug":["ghuntley.com","Geoffrey Huntley"],
"navz6xlcqekwdoeo3rhwpqbo":"ghughes",
"ifmi6fsburkl7pi4cxkxeaeq":["ghutchis","Geoff Hutchison"],
"warehlunjsko32kxdvf4vzgn":["ghuleh","Alice"],
"wttt7eul6zbqq4m7i7tbufgn":["ghurst","Garrett Hurst"],
"h7aihbxdvrr5toi5eq3ziyr2":["ghutyara","Gucci vampire 💉✨"],
"mz6erf7gfmhxmhhmfzwmya4k":["ghuraok","Ghuraok"],
"yfeknr2yhdv6xw3545bcabtd":"ghube",
"ghbt3qatz434bsudusz3pdff":"ghuman",
"vxr2npdgokghlirpog7euevw":["ghusna","Ghusna"],
"vi225wp65gnqmjb6prvgwrpl":"ghusse",
"r2psxwlp6zw4okc3ztz5fqfx":["ghoulteeth","ghu 🔞"],
"fzytrupnn2k7tf7osw4kaeej":["ghuruu","Brnt. 🦆"],
"mgcjoedmbdw5lne4a6mc5uvt":["ghust","Sjoerd"],
"j3q3y6gjwofjaxpg2hedccrt":"ghullghoul",
"lpmtbtbrfnlbkyylzu6xqci7":["ghuman1484","Parm Ghuman "],
"z2agpbbrndpr7cimbgzcwm2w":"ghukill",
"kssimeefmil2ylqypb3kw45q":["ghusisbest","Mosh"],
"feramv2jps5urh53hptjdirg":"ghu",
"c53noz6idcxfcfl75ncisjq3":"ghudson",
"45axpueglyyeg6frwmc5de3a":["ghurab","Ghurabalbayn"],
"cfcb2l5sqftd4bukmju442jh":["ghu-podcast","Gestern Heute Übermorgen"],
"5xzilbeaz7gyfdmyzrave45m":["ghurzlak","Ghurzlak"],
"x4fy63ljwjxb7mjqqsiwlsp4":["ghuul","Lil Ghuul"],
"yswhgyzlawz63gadi7j7ps25":["ghurt","Günter Hurt"],
"xc3lwfj7ehwwtl2zahpeaswb":"ghuertaramos",
"kbsqag6bsuda43uh7wldg7j4":"ghumph",
"jztzxncpp7csf6infcvzmqtw":["hulots-bassoon","SSRI Ghurkin"],
"7p2fwquh4zemy5knhcvhyzin":["iharryghuman","Harsimrat S. Ghumaan"],
"4yctfnd2tmbelapay2k4u5ns":["iytharghurab","Iythar Ghurab"],
"xpwrqo5ogd37kgryrhzyc4lv":["lostalghul","LordAlGhul "],
"w3bjc4owafivplpy6mje4jqy":["marsalghul","Mars Al'Ghul"],
"6t4zfvjfvbdvtpi5qxs2ay4x":["pghuijs","Petra Ghuijs"],
"e2ox3n6mzorfqevrck4dw2us":["rossalghul","Ross Al Ghul"],
"tpudxrjemy2wcszmlz733e5m":["witchgf","Ghuleh"]
}
