{
"5gpd6b7c3oheziu4m2cl5m6l":["gkountourides","Gabriella Kountourides (Κουντουριδου)"],
"l2dzg4543gvqzzfq7qixqtop":"gkost",
"neeo3644cslmnvtt2eh2aaeg":"gkon333",
"vpq34k2jn7dv2xtkxiigjdbd":"gkolstad",
"57mdzg62llwf2c364o47tcdm":["gkoe","gabe"],
"a2phuu7yy7vsq5q6xejobp4t":"gkono",
"a23xjnekckdyg72ykkohrqhn":"gko",
"6qfuvlec72255ua4xcbesdso":"gkohner",
"shemeqjf47egufc6yj6lrm4h":["gkosak","giovana "],
"wluo5htefrfzxhsu7zea3ntg":["gkordsmeier","Greg Kordsmeier"],
"75g4cmdanbbdgsxlzwn5kyeu":"gkosmo",
"6h3pnys5mwlzotavyi5ee6rn":["gkonings","Gerard Konings"],
"xncb47t7gppiy25is3nxg37a":["gkolayli","Göksu Kolaylı"],
"mkxcaxjcqfdftxr6pnk6jrle":["gkotsias","Grigorios Kotsias"],
"ys5mtoptyebtbospkoaar7di":"gkop",
"2boum7nfef5joh2c4qdeptpz":"gkonoplyov02",
"aed6gpsqlltwohwsbbtnzcnd":["gkornfeld","Günter Kornfeld"],
"ubhaohebvkxiwjx5zcbdcxl2":"gkolar",
"u5wdauaza3cbib4cvr6fm3sz":["lepasgrincheux","Gkoff"],
"7yx3jn4qxhwlwvyoq62jq747":["triagkouvas","Triantafyllos Gkouvas"]
}
