{
"dootvjooxrpu65y2ozl2jsap":["gksknyght","Silvex Knyght"],
"obpi42if7gdwnnkjqanq3hxe":["gksmwkr","하느작"],
"gurluxlppmhgsamifmihi7hk":"gkstories",
"6tha2gud5byvo7ytffmgwdig":["gkshen","庭院深深深幾許"],
"3hdim6sud5s4fnk7pd6rznkg":["gksemsid","냥"],
"h54k3tybzfzsodiws4ltasjk":["gkse16","Graham Henderson"],
"rdmsdy4p45yfh4xgpxffkqcl":"gksmf0929",
"pjmnug5yo42rolhfd4cv3oby":"gkslpys",
"cy46dp4zlyvqfonosicoj3e4":"gksrpa10",
"b2irbcth5b2gelhj7ogi6pbt":["gkskully","gkskully "],
"7v4e4pcmjm4alnaieaj7ix4r":"gksam10",
"w2cbp4frhx5zkp7zi5wb6vwe":["gkskahfl","帽ri"],
"smnz75i5zuyssvavj456vuoz":["gksmf","하늘"],
"o4kqzk7myvkc6nwivszfak7o":["gksmithlcw","Grant K. Smith (he / him)"],
"3kek3hc5oagqxufh5ztoj2gz":["gks13254","GkS_1325_4"],
"xpoqkdso6iawt5abdmccycmc":["gkssnl88","이백도"],
"luxhsotoqupw4zelyiwrlbra":"gkshearer",
"szanuddk6ynurhhxu33la5lu":["gks","Gemma Karstens-Smith"],
"jtxh2xmht7sk4omv5m4zqipe":["gksnl","하뉘"],
"xdokrvemddtd4nkaefggsxha":["gksnorl","Gökşin"]
}
